colormap/__init__.py
colormap/scripts/__init__.py
colormap/scripts/cli.py
rio_colormap-1.2.1.dist-info/LICENSE
rio_colormap-1.2.1.dist-info/METADATA
rio_colormap-1.2.1.dist-info/WHEEL
rio_colormap-1.2.1.dist-info/entry_points.txt
rio_colormap-1.2.1.dist-info/top_level.txt
rio_colormap-1.2.1.dist-info/RECORD
