Metadata-Version: 2.1
Name: rio-colormap
Version: 1.2.1
Summary: Rasterio CLI plugin example
Home-page: https://github.com/sgillies/rio-plugin-example
Author: Sean Gillies
Author-email: sean.gillies@gmail.com
License: BSD
Platform: UNKNOWN
Requires-Dist: click
Requires-Dist: cowpy
Requires-Dist: rasterio
Provides-Extra: test
Requires-Dist: pytest ; extra == 'test'
